gnre_automacao/__init__.py
gnre_automacao/gnre_ws.py
gnre_automacao/gnre_xml.py
gnre_automacao/nfe_parser.py
gnre_automacao/uf_additional_fields.json
gnre_automacao/uf_detalhamento.json
gnre_automacao-1.2.1.dist-info/licenses/LICENSE
gnre_automacao-1.2.1.dist-info/METADATA
gnre_automacao-1.2.1.dist-info/WHEEL
gnre_automacao-1.2.1.dist-info/top_level.txt
gnre_automacao-1.2.1.dist-info/RECORD
