Metadata-Version: 2.4
Name: gnre-automacao
Version: 1.2.1
Summary: Geração e envio de GNRE a partir de NF-e, com suporte a webservices e certificado PFX.
Author-email: Heitor Forner <heitor.forner@gmail.com>
License-Expression: MIT
Project-URL: Homepage, https://pypi.org/project/gnre-automacao/
Keywords: GNRE,NFe,ICMS,WebService,SOAP,PFX,Brasil
Classifier: Development Status :: 3 - Alpha
Classifier: Intended Audience :: Developers
Classifier: Topic :: Software Development :: Libraries
Classifier: Programming Language :: Python :: 3
Classifier: Programming Language :: Python :: 3 :: Only
Classifier: Programming Language :: Python :: 3.10
Classifier: Programming Language :: Python :: 3.11
Classifier: Programming Language :: Python :: 3.12
Classifier: Typing :: Typed
Requires-Python: >=3.10
License-File: LICENSE
Requires-Dist: cryptography>=41.0.0
Dynamic: license-file
